Metadata-Version: 2.1
Name: nbdev-cards
Version: 0.0.1
Summary: A sample of how to create a deck of cards lib using nbdev
Home-page: https://github.com/fastai/nbdev_cards/
Author: Jeremy Howard
Author-email: j@fast.ai
License: Apache Software License 2.0
Keywords: nbdev
Classifier: Development Status :: 3 - Alpha
Classifier: Intended Audience :: Developers
Classifier: Natural Language :: English
Classifier: Programming Language :: Python :: 3.9
Classifier: Programming Language :: Python :: 3.10
Classifier: License :: OSI Approved :: Apache Software License
Requires-Python: >=3.9
License-File: LICENSE
Provides-Extra: dev
